tests/__init__.py
tests/test.py
thunder/__init__.py
thunder/core.py
thunder/multi_obj.py
thunder/utilities.py
thunderfit/__init__.py
thunderfit/__main__.py
thunderfit/create_params.py
thunderfit/fit.py
thunderfit/map_scan.py
thunderfit/map_scan_tools.py
thunderfit/model_creation.py
thunderfit/multi_obj.py
thunderfit/normalisation.py
thunderfit/parsing.py
thunderfit/peak_finding.py
thunderfit/peak_fitting.py
thunderfit/plotting.py
thunderfit/raman_routine.py
thunderfit/rpca.py
thunderfit/thundobj.py
thunderfit/utilities.py
thunderfit/background/__init__.py
thunderfit/background/background_removal.py
thunderfit/background/scarf.py
thunderfit-1.7.2.5.dist-info/LICENSE
thunderfit-1.7.2.5.dist-info/METADATA
thunderfit-1.7.2.5.dist-info/WHEEL
thunderfit-1.7.2.5.dist-info/entry_points.txt
thunderfit-1.7.2.5.dist-info/top_level.txt
thunderfit-1.7.2.5.dist-info/RECORD
